README.rst
setup.py
halite/__init__.py
halite/aiding.py
halite/bottle.py
halite/genindex.py
halite/server_bottle.py
halite.egg-info/PKG-INFO
halite.egg-info/SOURCES.txt
halite.egg-info/dependency_links.txt
halite.egg-info/top_level.txt
halite/../LICENSE
halite/lattice/app/SaltStack-Logo.png
halite/lattice/app/SaltStackLogoBlackHoriz18.png
halite/lattice/app/appConfigSrvc.js
halite/lattice/app/favicon.ico
halite/lattice/app/main.css
halite/lattice/app/main.html
halite/lattice/app/main.js
halite/lattice/app/navbar.html
halite/lattice/app/robots.txt
halite/lattice/app/route.html
halite/lattice/app/util/appDataSrvc.js
halite/lattice/app/util/appDrtv.js
halite/lattice/app/util/appFltr.js
halite/lattice/app/util/appPrefSrvc.js
halite/lattice/app/util/appStoreSrvc.js
halite/lattice/app/util/appUtilSrvc.js
halite/lattice/app/util/demoSrvc.js
halite/lattice/app/util/errorReportingSrvc.js
halite/lattice/app/util/eventSrvc.js
halite/lattice/app/util/fetchActivesSrvc.js
halite/lattice/app/util/highstateCheckSrvc.js
halite/lattice/app/util/jobSrvc.js
halite/lattice/app/util/saltApiSrvc.js
halite/lattice/app/util/saltSrvc.js
halite/lattice/app/view/base.js
halite/lattice/app/view/console.html
halite/lattice/app/view/console.js
halite/lattice/app/view/home.html
halite/lattice/app/view/home.js
halite/lattice/app/view/project.html
halite/lattice/app/view/project.js
halite/lattice/lib/angular/angular-animate.min.js
halite/lattice/lib/angular/angular-animate.min.js.map
halite/lattice/lib/angular/angular-cookies.min.js
halite/lattice/lib/angular/angular-cookies.min.js.map
halite/lattice/lib/angular/angular-loader.js
halite/lattice/lib/angular/angular-loader.min.js
halite/lattice/lib/angular/angular-loader.min.js.map
halite/lattice/lib/angular/angular-resource.min.js
halite/lattice/lib/angular/angular-resource.min.js.map
halite/lattice/lib/angular/angular-route.min.js
halite/lattice/lib/angular/angular-route.min.js.map
halite/lattice/lib/angular/angular-sanitize.min.js
halite/lattice/lib/angular/angular-sanitize.min.js.map
halite/lattice/lib/angular/angular-touch.min.js
