Metadata-Version: 1.0
Name: halite
Version: 0.1.17
Summary: SaltStack Web UI
Home-page: https://github.com/saltstack/halite
Author: SaltStack Inc
Author-email: info@saltstack.com
License: Apache V2.0
Keywords: Salt Stack client side web application,web server
Platform: UNKNOWN
